<?xml version="1.0" encoding="UTF-8"?>

<StructureDefinition xmlns="http://hl7.org/fhir">
  <id value="artifact-name"/>
  <extension url="http://hl7.org/fhir/StructureDefinition/structuredefinition-wg">
    <valueCode value="cds"/>
  </extension>
  <extension url="http://hl7.org/fhir/StructureDefinition/structuredefinition-fmm">
    <valueInteger value="2"/>
  </extension>
  <extension url="http://hl7.org/fhir/StructureDefinition/structuredefinition-standards-status">
    <valueCode value="trial-use"/>
  </extension>
  <url value="http://hl7.org/fhir/StructureDefinition/artifact-name"/>
  <identifier>
    <system value="urn:ietf:rfc:3986"/>
    <value value="urn:oid:2.16.840.1.113883.4.642.5.1744"/>
  </identifier>
  <version value="5.0.0"/>
  <name value="ArtifactName"/>
  <title value="ArtifactName"/>
  <status value="active"/>
  <experimental value="false"/>
  <date value="2022-02-07"/>
  <publisher value="HL7 International / Clinical Decision Support"/>
  <contact>
    <telecom>
      <system value="url"/>
      <value value="http://www.hl7.org/Special/committees/dss"/>
    </telecom>
  </contact>
  <description value="A natural language name identifying the artifact. This name should be usable as an identifier for the module by machine processing applications such as code generation."/>
  <purpose value="This extension is defined to support representing artifact metadata on resources that are not already canonical resources that have the corresponding element, and that behave in a definitional way. For example, it would not be appropriate to use this extension on a patient-specific resource such as MedicationRequest or CarePlan. For resources where this element was added in R5, the cross-version extension should be used rather than this extension (ConditionDefinition,ObservationDefinition,SpecimenDefinition,SubscriptionTopic)."/>
  <fhirVersion value="5.0.0"/>
  <mapping>
    <identity value="rim"/>
    <uri value="http://hl7.org/v3"/>
    <name value="RIM Mapping"/>
  </mapping>
  <kind value="complex-type"/>
  <abstract value="false"/>
  <context><type value="element"/><expression value="ClinicalUseDefinition"/></context>
  <context><type value="element"/><expression value="ConditionDefinition"/></context>
  <context><type value="element"/><expression value="DeviceDefinition"/></context>
  <context><type value="element"/><expression value="Group"/></context>
  <context><type value="element"/><expression value="Medication"/></context>
  <context><type value="element"/><expression value="MedicationKnowledge"/></context>
  <context><type value="element"/><expression value="ObservationDefinition"/></context>
  <context><type value="element"/><expression value="SpecimenDefinition"/></context>
  <context><type value="element"/><expression value="Substance"/></context>
  <context><type value="element"/><expression value="SubstanceDefinition"/></context>
  <context><type value="element"/><expression value="SubscriptionTopic"/></context>
  <type value="Extension"/>
  <baseDefinition value="http://hl7.org/fhir/StructureDefinition/Extension"/>
  <derivation value="constraint"/>
  <differential>
    <element id="Extension">
      <path value="Extension"/>
      <short value="Name for this artifact (computer friendly)"/>
      <definition value="A natural language name identifying the artifact. This name should be usable as an identifier for the module by machine processing applications such as code generation."/>
      <comment value="The name is not expected to be globally unique. The name should be a simple alphanumeric type name to ensure that it is machine-processing friendly."/>
      <min value="0"/>
      <max value="1"/>
    </element>
    <element id="Extension.extension">
      <path value="Extension.extension"/>
      <max value="0"/>
    </element>
    <element id="Extension.url">
      <path value="Extension.url"/>
      <fixedUri value="http://hl7.org/fhir/StructureDefinition/artifact-name"/>
    </element>
    <element id="Extension.value[x]">
      <path value="Extension.value[x]"/>
      <min value="1"/>
      <type>
        <code value="string"/>
      </type>
    </element>
  </differential>
</StructureDefinition>
